{
  "tags": {
    "allowUnknownTags": true,
    "dictionaries": [
      "jsdoc"
    ]
  },
  "source": {
    "include": [
      "README.md"
    ],
    "includePattern": "",
    "excludePattern": ""
  },
  "plugins": [
    "plugins/markdown"
  ],
  "templates": {
    "systemName": "Extension CLI",
    "systemSummary": "Command-line utility tool that speeds up chrome extension development by providing a systematic way to build, test and document extension projects.",
    "systemColor": "#222136",
    "footer": "<a class=\"github-button\" href=\"https://github.com/mobilefirstllc/extension-cli\" data-icon=\"octicon-star\" data-size=\"large\" aria-label=\"Star mobilefirstllc/extension-cli on GitHub\">Star</a> &nbsp; <a class=\"github-button\" href=\"https://github.com/mobilefirstllc/extension-cli/fork\" data-icon=\"octicon-repo-forked\" data-size=\"large\" aria-label=\"Fork mobilefirstllc/extension-cli on GitHub\">Fork</a> &nbsp; <a class=\"github-button\" href=\"https://github.com/mobilefirstllc/extension-cli/issues\" data-icon=\"octicon-issue-opened\" data-size=\"large\" aria-label=\"Issue mobilefirstllc/extension-cli on GitHub\">Issue</a> &nbsp; <a class=\"github-button\" href=\"https://github.com/mobilefirstllc/extension-cli/subscription\" data-icon=\"octicon-eye\" data-size=\"large\" aria-label=\"Watch mobilefirstllc/extension-cli on GitHub\">Watch</a><br/><br/>",
    "copyright": "Extension CLI is made by <a href='https://mobilefirst.me'>Mobile First</a> in the \uD83C\uDF51 state.",
    "includeDate": "true",
    "dateFormat": "MMM YYYY",
    "inlineNav": "true",
    "inverseNav": "false",
    "linenums": "true",
    "showTableOfContents": "true",
    "showAccessFilter": "true",
    "collapseSymbols": "false",
    "methodHeadingReturns": "false",
    "outputSourceFiles": "true",
    "outputSourcePath": "true",
    "search": "false",
    "stylesheets": [
      "data:text/css;base64,YXJ0aWNsZSBwLCBhcnRpY2xlIHVsLCBhcnRpY2xlIHRhYmxle2ZvbnQtc2l6ZTogMS4zZW07bGluZS1oZWlnaHQ6IDEuODt9aDMsaDQsaDUsaDZ7bWFyZ2luLXRvcDoyZW19"
    ],
    "scripts": [
      "https://buttons.github.io/buttons.js"
    ],
    "navMembers": [
      {
        "kind": "tutorial",
        "title": "Guide",
        "summary": "Learn how to use extension CLI"
      }
    ],
    "analytics": {
      "ua": "UA-129118591-4",
      "domain": "https://mobilefirstllc.github.io/"
    },
    "favicon": "./assets/img/128x128.png"
  },
  "opts": {
    "destination": "./docs",
    "encoding": "utf8",
    "private": true,
    "recurse": true,
    "template": "./node_modules/foodoc/template"
  }
}
